[
    {
        "id": "bird-box",
        "title": "Bird Box",
        "url":"https://iili.io/HKhQiWG.jpg"
    },
    {
        "id": "colombiana",
        "title": "Colombiana - Em busca de vingança",
        "url":"https://iili.io/HKhQPxs.jpg"
    },
    {
        "id": "enola-holmes",
        "title": "Enola Holmes",
        "url":"https://iili.io/HKhQtg2.jpg"
    },
    {
        "id": "fratura",
        "title": "Fratura",
        "url":"https://iili.io/HKhQpe9.jpg"
    },
    {
        "id": "holidate",
        "title": "Holidate",
        "url":"https://iili.io/HKhZdsj.jpg"
    },
    {
        "id": "contratiempo",
        "title": "Contratiempo",
        "url":"https://iili.io/HKhZKgV.jpg"
    },
    {
        "id": "misterio-no-mediterraneo",
        "title": "Mistério no mediterrâneo",
        "url":"https://iili.io/HKhZCe1.jpg"
    },
    {
        "id": "skyscraper",
        "title": "Skyscraper",
        "url":"https://iili.io/HKhZuqv.jpg"
    },
    {
        "id": "um-senhor-estagiario",
        "title": "Um senhor estagiário",
        "url":"https://iili.io/HKhZILJ.jpg"
    },
    {
        "id": "vozes",
        "title": "Vozes",
        "url":"https://iili.io/HKhZ7dN.jpg"
    }
]